echobox/__init__.py
echobox/main.py
pnu_echobox-1.2.2.data/data/man/man1/echobox.1.gz
pnu_echobox-1.2.2.dist-info/License
pnu_echobox-1.2.2.dist-info/METADATA
pnu_echobox-1.2.2.dist-info/WHEEL
pnu_echobox-1.2.2.dist-info/entry_points.txt
pnu_echobox-1.2.2.dist-info/top_level.txt
pnu_echobox-1.2.2.dist-info/RECORD
